govuk_frontend_jinja/__init__.py
govuk_frontend_jinja/templates/template.html
govuk_frontend_jinja/templates/components/accordion/macro.html
govuk_frontend_jinja/templates/components/back-link/macro.html
govuk_frontend_jinja/templates/components/breadcrumbs/macro.html
govuk_frontend_jinja/templates/components/button/macro.html
govuk_frontend_jinja/templates/components/character-count/macro.html
govuk_frontend_jinja/templates/components/checkboxes/macro.html
govuk_frontend_jinja/templates/components/cookie-banner/macro.html
govuk_frontend_jinja/templates/components/date-input/macro.html
govuk_frontend_jinja/templates/components/details/macro.html
govuk_frontend_jinja/templates/components/error-message/macro.html
govuk_frontend_jinja/templates/components/error-summary/macro.html
govuk_frontend_jinja/templates/components/exit-this-page/macro.html
govuk_frontend_jinja/templates/components/fieldset/macro.html
govuk_frontend_jinja/templates/components/file-upload/macro.html
govuk_frontend_jinja/templates/components/footer/macro.html
govuk_frontend_jinja/templates/components/header/macro.html
govuk_frontend_jinja/templates/components/hint/macro.html
govuk_frontend_jinja/templates/components/input/macro.html
govuk_frontend_jinja/templates/components/inset-text/macro.html
govuk_frontend_jinja/templates/components/label/macro.html
govuk_frontend_jinja/templates/components/notification-banner/macro.html
govuk_frontend_jinja/templates/components/pagination/macro.html
govuk_frontend_jinja/templates/components/panel/macro.html
govuk_frontend_jinja/templates/components/password-input/macro.html
govuk_frontend_jinja/templates/components/phase-banner/macro.html
govuk_frontend_jinja/templates/components/radios/macro.html
govuk_frontend_jinja/templates/components/select/macro.html
govuk_frontend_jinja/templates/components/service-navigation/macro.html
govuk_frontend_jinja/templates/components/skip-link/macro.html
govuk_frontend_jinja/templates/components/summary-list/macro.html
govuk_frontend_jinja-3.10.0.dist-info/licenses/LICENSE
govuk_frontend_jinja-3.10.0.dist-info/METADATA
govuk_frontend_jinja-3.10.0.dist-info/WHEEL
govuk_frontend_jinja-3.10.0.dist-info/top_level.txt
govuk_frontend_jinja-3.10.0.dist-info/RECORD
