Metadata-Version: 2.4
Name: govuk-frontend-jinja
Version: 3.10.0
Summary: GOV.UK Frontend Jinja Macros
Author: Andy Mantell
Author-email: Matt Shaw <matthew.shaw@landregistry.gov.uk>
Maintainer-email: Matt Shaw <matthew.shaw@landregistry.gov.uk>
License-Expression: MIT
Project-URL: Homepage, https://github.com/LandRegistry/govuk-frontend-jinja
Project-URL: Issues, https://github.com/LandRegistry/govuk-frontend-jinja/issues
Project-URL: Changelog, https://github.com/LandRegistry/govuk-frontend-jinja/blob/main/CHANGELOG.md
Keywords: component,design system,frontend,govuk-frontend,govuk,jinja,macros
Classifier: Development Status :: 5 - Production/Stable
Classifier: Environment :: Web Environment
Classifier: Intended Audience :: Developers
Classifier: Operating System :: OS Independent
Classifier: Programming Language :: Python :: 3.10
Classifier: Programming Language :: Python :: 3.11
Classifier: Programming Language :: Python :: 3.12
Classifier: Programming Language :: Python :: 3.13
Classifier: Programming Language :: Python :: 3.14
Classifier: Topic :: Software Development :: Code Generators
Classifier: Topic :: Software Development :: User Interfaces
Classifier: Topic :: Text Processing :: Markup :: HTML
Requires-Python: >=3.10
License-File: LICENSE
Requires-Dist: jinja2!=3.0.0,!=3.0.1
Dynamic: license-file
